langchain_together/__init__.py
langchain_together/chat_models.py
langchain_together/embeddings.py
langchain_together/llms.py
langchain_together/py.typed
gigachain_together-0.1.5.dist-info/LICENSE
gigachain_together-0.1.5.dist-info/METADATA
gigachain_together-0.1.5.dist-info/WHEEL
gigachain_together-0.1.5.dist-info/RECORD
